dblite/__init__.py
dblite/api.py
dblite/util.py
dblite/engines/__init__.py
dblite/engines/postgres.py
dblite/engines/sqlite.py
dblite-1.3.3.dist-info/LICENSE.md
dblite-1.3.3.dist-info/METADATA
dblite-1.3.3.dist-info/WHEEL
dblite-1.3.3.dist-info/top_level.txt
dblite-1.3.3.dist-info/RECORD
