Metadata-Version: 2.1
Name: dblite
Version: 1.3.3
Summary: Simple query interface for SQL databases
Home-page: https://github.com/suurjaak/dblite
Author: Erki Suurjaak
Author-email: erki@lap.ee
License: MIT
Keywords: SQL SQLite Postgres psycopg2
Platform: any
Classifier: Development Status :: 4 - Beta
Classifier: License :: OSI Approved :: MIT License
Classifier: Intended Audience :: Developers
Classifier: Topic :: Database
Classifier: Topic :: Software Development :: Libraries
Classifier: Programming Language :: Python
Classifier: Programming Language :: Python :: 2
Classifier: Programming Language :: Python :: 2.7
Classifier: Programming Language :: Python :: 3
Requires-Python: >=2.7
License-File: LICENSE.md
Requires-Dist: six
